{
    "format_version": "1.10.0",
    "minecraft:client_entity": {
        "description": {
            "identifier": "hp4_paint:spray_can",
            "materials": {
                "default": "hp4_paint.outline_base",
                "painting": "spider",
                "outline": "hp4_paint.outline"
            },
            "textures": {
                "default1": "textures/hp/mp/furnitures/spray1",
                "default2": "textures/hp/mp/furnitures/spray2",
                "default3": "textures/hp/mp/furnitures/spray3",
                "default4": "textures/hp/mp/furnitures/spray4",
                "default5": "textures/hp/mp/furnitures/spray5",
                "default6": "textures/hp/mp/furnitures/spray6",
                "default7": "textures/hp/mp/furnitures/spray7",
                "default8": "textures/hp/mp/furnitures/spray8",
                "default9": "textures/hp/mp/furnitures/spray9",
                "default10": "textures/hp/mp/furnitures/spray10",
                "default11": "textures/hp/mp/furnitures/spray11",
                "default12": "textures/hp/mp/furnitures/spray12",
                "default13": "textures/hp/mp/furnitures/spray13",
                "default14": "textures/hp/mp/furnitures/spray14",
                "default15": "textures/hp/mp/furnitures/spray15",
                "default16": "textures/hp/mp/furnitures/spray16",
                "outline": "textures/hp/mp/outline"
            },
            "geometry": {
                "default": "geometry.hp4_paint.spray_can",
                "outline": "geometry.hp4_paint.spray_can.outline"
            },
            "render_controllers": [
                {
                    "controller.render.hp4_paint.outline_spray_can": "q.property('hp4_paint:outline')"
                },
                "controller.render.hp4_paint.spray_can"
            ],
            "spawn_egg": {
                "texture": "hp4_paint:spray_can"
            },
            "animations": {
                "cardinal_rotation": "animation.hp4_paint.cardinal_rotation"
            },
            "scripts": {
                "animate": [
                    "cardinal_rotation"
                ]
            }
        }
    }
}